Metadata-Version: 1.1
Name: PyAcademy
Version: 0.0.5
Summary: Academic Helper
Home-page: https://github.com/chinkushah/PyAcademy.git
Author: Rohan Shah and Gaurav Thakur
Author-email: rohan.h.shah.03@gmail.com, gaugau939@gmail.com
License: MIT
Keywords: education
Platform: UNKNOWN
Classifier: Development Status :: 5 - Production/Stable
Classifier: Intended Audience :: Education
Classifier: Operating System :: Microsoft :: Windows :: Windows 10
Classifier: License :: OSI Approved :: MIT License
Classifier: Programming Language :: Python :: 3
